{
  "feature": "goodending:cypress_tree_filtered",
  "placement": [
    {
      "type": "minecraft:in_square"
    },
    {
      "type": "minecraft:surface_water_depth_filter",
      "max_water_depth": 8
    },
    {
      "type": "minecraft:count",
      "count": {
        "type": "minecraft:weighted_list",
        "distribution": [
          {
            "data": 4,
            "weight": 1
          },
          {
            "data": 8,
            "weight": 1
          }
        ]
      }
    },
    {
      "type": "minecraft:heightmap",
      "heightmap": "OCEAN_FLOOR"
    },
    {
      "type": "minecraft:biome"
    }
  ]
}